verilog/src/counter.v
/*
	Simple counter with generic bitwidth.
*/

`default_nettype none
`ifndef __COUNTER__
`define __COUNTER__

module counter
#(
	parameter BW = 8 // optional parameter
) (	
	// define I/O's of the module
	input					clk_i,			// clock
	input					rst_i,			// reset 
	output wire [BW-1:0]	counter_val_o 	// counter value
);
	// start the module implementation
	
	// register to store the counter value
	reg [BW-1:0] counter_val;
	
	// gets active always when a positive edge of the clock signal occours
	always @(posedge clk_i) begin
		if (rst_i == 1'b1) begin
			// if reset is enabled
			counter_val <= {BW{1'b0}}; //reset the counter value
		end else begin
			//increment the counter value by 1
			// replicate 1'b0 (BW-1) times and concatenate vector with 1'b1
			counter_val <= counter_val + {{(BW-1){1'b0}}, 1'b1}; // If BW = 8 --> 8'b00000001
		end
	end
	
	// assign the counter value to the output
	assign counter_val_o = counter_val; 
	
endmodule // counter

`endif
`default_nettype wire

verilog/tb/counter_tb.v
/*
	Simple testbench for the counter.
*/

`timescale 1ns / 1ns // `timescale <time_unit> / <time_precision>

`include "../src/counter.v"

module counter_tb;

	parameter BW = 3;
	
	// inputs
	reg 		rst_i = 1'b1;
	reg 		clk_i = 1'b0;
	wire [BW-1:0] 	cnt_val; 
	
	//DUT
	counter 
		#(BW)
	counter_dut (
		.clk_i(clk_i),
		.rst_i(rst_i),
		.counter_val_o(cnt_val)
	);
	
	//Generate clock
	/* verilator lint_off STMTDLY */
	always #5 clk_i = ~clk_i; // wait 5 time units (e.g. 5ns)
	/* verilator lint_on STMTDLY */
	
	initial begin
		$dumpfile("counter_tb.vcd");
		$dumpvars;
	
		/* verilator lint_off STMTDLY */
		#50 rst_i = 1'b0; // deassert reset
		#200 $finish; // finish
		/* verilator lint_on STMTDLY */
	end
endmodule // counter_tb

verilog/tb/counter_tb.vcd
$date
	Thu Oct  2 17:00:12 2025
$end
$version
	Icarus Verilog
$end
$timescale
	1ns
$end
$scope module counter_tb $end
$var wire 3 ! cnt_val [2:0] $end
$var parameter 32 " BW $end
$var reg 1 # clk_i $end
$var reg 1 $ rst_i $end
$scope module counter_dut $end
$var wire 1 # clk_i $end
$var wire 3 % counter_val_o [2:0] $end
$var wire 1 $ rst_i $end
$var parameter 32 & BW $end
$var reg 3 ' counter_val [2:0] $end
$upscope $end
$upscope $end
$enddefinitions $end
$comment Show the parameter values. $end
$dumpall
b11 &
b11 "
$end
#0
$dumpvars
bx '
bx %
1$
0#
bx !
$end
#5
b0 !
b0 %
b0 '
1#
#10
0#
#15
1#
#20
0#
#25
1#
#30
0#
#35
1#
#40
0#
#45
1#
#50
0#
0$
#55
b1 !
b1 %
b1 '
1#
#60
0#
#65
b10 !
b10 %
b10 '
1#
#70
0#
#75
b11 !
b11 %
b11 '
1#
#80
0#
#85
b100 !
b100 %
b100 '
1#
#90
0#
#95
b101 !
b101 %
b101 '
1#
#100
0#
#105
b110 !
b110 %
b110 '
1#
#110
0#
#115
b111 !
b111 %
b111 '
1#
#120
0#
#125
b0 !
b0 %
b0 '
1#
#130
0#
#135
b1 !
b1 %
b1 '
1#
#140
0#
#145
b10 !
b10 %
b10 '
1#
#150
0#
#155
b11 !
b11 %
b11 '
1#
#160
0#
#165
b100 !
b100 %
b100 '
1#
#170
0#
#175
b101 !
b101 %
b101 '
1#
#180
0#
#185
b110 !
b110 %
b110 '
1#
#190
0#
#195
b111 !
b111 %
b111 '
1#
#200
0#
#205
b0 !
b0 %
b0 '
1#
#210
0#
#215
b1 !
b1 %
b1 '
1#
#220
0#
#225
b10 !
b10 %
b10 '
1#
#230
0#
#235
b11 !
b11 %
b11 '
1#
#240
0#
#245
b100 !
b100 %
b100 '
1#
