verilog/src/counter.v
/*
	Simple counter with generic bitwidth.
*/

`default_nettype none
`ifndef __COUNTER__
`define __COUNTER__

module counter
#(
	parameter BW = 8 // optional parameter
) (	
	// define I/O's of the module
	input					clk_i,			// clock
	input					rst_i,			// reset 
	output wire [BW-1:0]	counter_val_o 	// counter value
);
	// start the module implementation
	
	// register to store the counter value
	reg [BW-1:0] counter_val;
	
	// gets active always when a positive edge of the clock signal occours
	always @(posedge clk_i) begin 
		if (rst_i == 1'b1) begin
			// if reset is enabled
			counter_val <= {BW{1'b0}}; //reset the counter value
		end else begin
			//increment the counter value by 1
			// replicate 1'b0 (BW-1) times and concatenate vector with 1'b1
			counter_val <= counter_val + {{(BW-1){1'b0}}, 1'b1}; // If BW = 8 --> 8'b00000001
		end
	end
	
	// assign the counter value to the output
	assign counter_val_o = counter_val; 
	
endmodule // counter

`endif
`default_nettype wire

verilog/src/tt_um_counter_top.v
/*
 * Copyright (c) 2024 Your Name
 * SPDX-License-Identifier: Apache-2.0
 */

`default_nettype none

`include "counter.v"

module tt_um_counter_top (
    input  wire [7:0] ui_in,    // Dedicated inputs
    output wire [7:0] uo_out,   // Dedicated outputs
    input  wire [7:0] uio_in,   // IOs: Input path
    output wire [7:0] uio_out,  // IOs: Output path
    output wire [7:0] uio_oe,   // IOs: Enable path (active high: 0=input, 1=output)
    input  wire       ena,      // always 1 when the design is powered, so you can ignore it
    input  wire       clk,      // clock
    input  wire       rst_n     // reset_n - low to reset
);
	
	localparam BW = 8;
	
	// Declare wire to hold counter output
	wire [BW-1:0] counter_val;

	// Instantiate the counter module
	counter #(
		.BW(BW)  						// Set bit width parameter to local parameter BW
	) counter_inst (
		.clk_i(clk),                    // Connect clock
		.rst_i(~rst_n),                 // Connect reset (inverted since rst_n is active low)
		.counter_val_o(counter_val)     // Connect counter output
	);
  
	// All output pins must be assigned. If not used, assign to 0.
	assign uo_out  = counter_val;     	// Output the counter value
	assign uio_out = 0;
	assign uio_oe  = 0;

	// List all unused inputs to prevent warnings
	wire _unused = &{ena, ui_in, uio_in, 1'b0};

endmodule

verilog/tb/tt_um_counter_top_tb.v
/*
	Simple testbench for tt_um_counter_top.
*/

`timescale 1ns / 1ns // `timescale <time_unit> / <time_precision>

//`include "../src/tt_um_counter_top.v"

module tt_um_counter_top_tb;

	// inputs for tt_um_example
	reg [7:0] ui_in = 8'h00;
	reg [7:0] uio_in = 8'h00;
	reg ena = 1'b1;
	reg clk = 1'b0;
	reg rst_n = 1'b0;  // Active low reset
	
	// outputs from tt_um_example
	wire [7:0] 	uo_out;
	wire [7:0] 	uio_out;
	wire [7:0] 	uio_oe;
	
	//DUT
	tt_um_counter_top tt_um_counter_top_dut (
		.ui_in(ui_in),
		.uo_out(uo_out),
		.uio_in(uio_in),
		.uio_out(uio_out),
		.uio_oe(uio_oe),
		.ena(ena),
		.clk(clk),
		.rst_n(rst_n)
	);
	
	//Generate clock
	/* verilator lint_off STMTDLY */
	always #5 clk = ~clk; // wait 5 time units (e.g. 5ns)
	/* verilator lint_on STMTDLY */
	
	initial begin
		$dumpfile("tt_um_counter_top_tb.vcd");
		$dumpvars;
	
		/* verilator lint_off STMTDLY */
		#50 rst_n = 1'b1; // deassert reset
		#3000 $finish; // finish
		/* verilator lint_on STMTDLY */
	end
endmodule // tt_um_counter_top_tb

verilog/tb/tt_um_counter_top_tb.vcd
$date
	Mon Oct  6 23:11:33 2025
$end
$version
	Icarus Verilog
$end
$timescale
	1ns
$end
$scope module tt_um_counter_top_tb $end
$var wire 8 ! uio_oe [7:0] $end
$var wire 8 " uio_out [7:0] $end
$var wire 8 # uo_out [7:0] $end
$var reg 1 $ clk $end
$var reg 1 % ena $end
$var reg 1 & rst_n $end
$var reg 8 ' ui_in [7:0] $end
$var reg 8 ( uio_in [7:0] $end
$scope module tt_um_counter_top_dut $end
$var wire 1 $ clk $end
$var wire 1 % ena $end
$var wire 1 & rst_n $end
$var wire 8 ) ui_in [7:0] $end
$var wire 8 * uio_in [7:0] $end
$var wire 8 + uio_oe [7:0] $end
$var wire 8 , uio_out [7:0] $end
$var wire 8 - uo_out [7:0] $end
$var wire 8 . counter_val [7:0] $end
$var wire 1 / _unused $end
$var parameter 32 0 BW $end
$scope module counter_inst $end
$var wire 1 $ clk_i $end
$var wire 8 1 counter_val_o [7:0] $end
$var wire 1 2 rst_i $end
$var parameter 32 3 BW $end
$var reg 8 4 counter_val [7:0] $end
$upscope $end
$upscope $end
$upscope $end
$enddefinitions $end
$comment Show the parameter values. $end
$dumpall
b1000 3
b1000 0
$end
#0
$dumpvars
bx 4
12
bx 1
0/
bx .
bx -
b0 ,
b0 +
b0 *
b0 )
b0 (
b0 '
0&
1%
0$
bx #
b0 "
b0 !
$end
#5
b0 #
b0 -
b0 .
b0 1
b0 4
1$
#10
0$
#15
1$
#20
0$
#25
1$
#30
0$
#35
1$
#40
0$
#45
1$
#50
02
0$
1&
#55
b1 #
b1 -
b1 .
b1 1
b1 4
1$
#60
0$
#65
b10 #
b10 -
b10 .
b10 1
b10 4
1$
#70
0$
#75
b11 #
b11 -
b11 .
b11 1
b11 4
1$
#80
0$
#85
b100 #
b100 -
b100 .
b100 1
b100 4
1$
#90
0$
#95
b101 #
b101 -
b101 .
b101 1
b101 4
1$
#100
0$
#105
b110 #
b110 -
b110 .
b110 1
b110 4
1$
#110
0$
#115
b111 #
b111 -
b111 .
b111 1
b111 4
1$
#120
0$
#125
b1000 #
b1000 -
b1000 .
b1000 1
b1000 4
1$
#130
0$
#135
b1001 #
b1001 -
b1001 .
b1001 1
b1001 4
1$
#140
0$
#145
b1010 #
b1010 -
b1010 .
b1010 1
b1010 4
1$
#150
0$
#155
b1011 #
b1011 -
b1011 .
b1011 1
b1011 4
1$
#160
0$
#165
b1100 #
b1100 -
b1100 .
b1100 1
b1100 4
1$
#170
0$
#175
b1101 #
b1101 -
b1101 .
b1101 1
b1101 4
1$
#180
0$
#185
b1110 #
b1110 -
b1110 .
b1110 1
b1110 4
1$
#190
0$
#195
b1111 #
b1111 -
b1111 .
b1111 1
b1111 4
1$
#200
0$
#205
b10000 #
b10000 -
b10000 .
b10000 1
b10000 4
1$
#210
0$
#215
b10001 #
b10001 -
b10001 .
b10001 1
b10001 4
1$
#220
0$
#225
b10010 #
b10010 -
b10010 .
b10010 1
b10010 4
1$
#230
0$
#235
b10011 #
b10011 -
b10011 .
b10011 1
b10011 4
1$
#240
0$
#245
b10100 #
b10100 -
b10100 .
b10100 1
b10100 4
1$
#250
0$
#255
b10101 #
b10101 -
b10101 .
b10101 1
b10101 4
1$
#260
0$
#265
b10110 #
b10110 -
b10110 .
b10110 1
b10110 4
1$
#270
0$
#275
b10111 #
b10111 -
b10111 .
b10111 1
b10111 4
1$
#280
0$
#285
b11000 #
b11000 -
b11000 .
b11000 1
b11000 4
1$
#290
0$
#295
b11001 #
b11001 -
b11001 .
b11001 1
b11001 4
1$
#300
0$
#305
b11010 #
b11010 -
b11010 .
b11010 1
b11010 4
1$
#310
0$
#315
b11011 #
b11011 -
b11011 .
b11011 1
b11011 4
1$
#320
0$
#325
b11100 #
b11100 -
b11100 .
b11100 1
b11100 4
1$
#330
0$
#335
b11101 #
b11101 -
b11101 .
b11101 1
b11101 4
1$
#340
0$
#345
b11110 #
b11110 -
b11110 .
b11110 1
b11110 4
1$
#350
0$
#355
b11111 #
b11111 -
b11111 .
b11111 1
b11111 4
1$
#360
0$
#365
b100000 #
b100000 -
b100000 .
b100000 1
b100000 4
1$
#370
0$
#375
b100001 #
b100001 -
b100001 .
b100001 1
b100001 4
1$
#380
0$
#385
b100010 #
b100010 -
b100010 .
b100010 1
b100010 4
1$
#390
0$
#395
b100011 #
b100011 -
b100011 .
b100011 1
b100011 4
1$
#400
0$
#405
b100100 #
b100100 -
b100100 .
b100100 1
b100100 4
1$
#410
0$
#415
b100101 #
b100101 -
b100101 .
b100101 1
b100101 4
1$
#420
0$
#425
b100110 #
b100110 -
b100110 .
b100110 1
b100110 4
1$
#430
0$
#435
b100111 #
b100111 -
b100111 .
b100111 1
b100111 4
1$
#440
0$
#445
b101000 #
b101000 -
b101000 .
b101000 1
b101000 4
1$
#450
0$
#455
b101001 #
b101001 -
b101001 .
b101001 1
b101001 4
1$
#460
0$
#465
b101010 #
b101010 -
b101010 .
b101010 1
b101010 4
1$
#470
0$
#475
b101011 #
b101011 -
b101011 .
b101011 1
b101011 4
1$
#480
0$
#485
b101100 #
b101100 -
b101100 .
b101100 1
b101100 4
1$
#490
0$
#495
b101101 #
b101101 -
b101101 .
b101101 1
b101101 4
1$
#500
0$
#505
b101110 #
b101110 -
b101110 .
b101110 1
b101110 4
1$
#510
0$
#515
b101111 #
b101111 -
b101111 .
b101111 1
b101111 4
1$
#520
0$
#525
b110000 #
b110000 -
b110000 .
b110000 1
b110000 4
1$
#530
0$
#535
b110001 #
b110001 -
b110001 .
b110001 1
b110001 4
1$
#540
0$
#545
b110010 #
b110010 -
b110010 .
b110010 1
b110010 4
1$
#550
0$
#555
b110011 #
b110011 -
b110011 .
b110011 1
b110011 4
1$
#560
0$
#565
b110100 #
b110100 -
b110100 .
b110100 1
b110100 4
1$
#570
0$
#575
b110101 #
b110101 -
b110101 .
b110101 1
b110101 4
1$
#580
0$
#585
b110110 #
b110110 -
b110110 .
b110110 1
b110110 4
1$
#590
0$
#595
b110111 #
b110111 -
b110111 .
b110111 1
b110111 4
1$
#600
0$
#605
b111000 #
b111000 -
b111000 .
b111000 1
b111000 4
1$
#610
0$
#615
b111001 #
b111001 -
b111001 .
b111001 1
b111001 4
1$
#620
0$
#625
b111010 #
b111010 -
b111010 .
b111010 1
b111010 4
1$
#630
0$
#635
b111011 #
b111011 -
b111011 .
b111011 1
b111011 4
1$
#640
0$
#645
b111100 #
b111100 -
b111100 .
b111100 1
b111100 4
1$
#650
0$
#655
b111101 #
b111101 -
b111101 .
b111101 1
b111101 4
1$
#660
0$
#665
b111110 #
b111110 -
b111110 .
b111110 1
b111110 4
1$
#670
0$
#675
b111111 #
b111111 -
b111111 .
b111111 1
b111111 4
1$
#680
0$
#685
b1000000 #
b1000000 -
b1000000 .
b1000000 1
b1000000 4
1$
#690
0$
#695
b1000001 #
b1000001 -
b1000001 .
b1000001 1
b1000001 4
1$
#700
0$
#705
b1000010 #
b1000010 -
b1000010 .
b1000010 1
b1000010 4
1$
#710
0$
#715
b1000011 #
b1000011 -
b1000011 .
b1000011 1
b1000011 4
1$
#720
0$
#725
b1000100 #
b1000100 -
b1000100 .
b1000100 1
b1000100 4
1$
#730
0$
#735
b1000101 #
b1000101 -
b1000101 .
b1000101 1
b1000101 4
1$
#740
0$
#745
b1000110 #
b1000110 -
b1000110 .
b1000110 1
b1000110 4
1$
#750
0$
#755
b1000111 #
b1000111 -
b1000111 .
b1000111 1
b1000111 4
1$
#760
0$
#765
b1001000 #
b1001000 -
b1001000 .
b1001000 1
b1001000 4
1$
#770
0$
#775
b1001001 #
b1001001 -
b1001001 .
b1001001 1
b1001001 4
1$
#780
0$
#785
b1001010 #
b1001010 -
b1001010 .
b1001010 1
b1001010 4
1$
#790
0$
#795
b1001011 #
b1001011 -
b1001011 .
b1001011 1
b1001011 4
1$
#800
0$
#805
b1001100 #
b1001100 -
b1001100 .
b1001100 1
b1001100 4
1$
#810
0$
#815
b1001101 #
b1001101 -
b1001101 .
b1001101 1
b1001101 4
1$
#820
0$
#825
b1001110 #
b1001110 -
b1001110 .
b1001110 1
b1001110 4
1$
#830
0$
#835
b1001111 #
b1001111 -
b1001111 .
b1001111 1
b1001111 4
1$
#840
0$
#845
b1010000 #
b1010000 -
b1010000 .
b1010000 1
b1010000 4
1$
#850
0$
#855
b1010001 #
b1010001 -
b1010001 .
b1010001 1
b1010001 4
1$
#860
0$
#865
b1010010 #
b1010010 -
b1010010 .
b1010010 1
b1010010 4
1$
#870
0$
#875
b1010011 #
b1010011 -
b1010011 .
b1010011 1
b1010011 4
1$
#880
0$
#885
b1010100 #
b1010100 -
b1010100 .
b1010100 1
b1010100 4
1$
#890
0$
#895
b1010101 #
b1010101 -
b1010101 .
b1010101 1
b1010101 4
1$
#900
0$
#905
b1010110 #
b1010110 -
b1010110 .
b1010110 1
b1010110 4
1$
#910
0$
#915
b1010111 #
b1010111 -
b1010111 .
b1010111 1
b1010111 4
1$
#920
0$
#925
b1011000 #
b1011000 -
b1011000 .
b1011000 1
b1011000 4
1$
#930
0$
#935
b1011001 #
b1011001 -
b1011001 .
b1011001 1
b1011001 4
1$
#940
0$
#945
b1011010 #
b1011010 -
b1011010 .
b1011010 1
b1011010 4
1$
#950
0$
#955
b1011011 #
b1011011 -
b1011011 .
b1011011 1
b1011011 4
1$
#960
0$
#965
b1011100 #
b1011100 -
b1011100 .
b1011100 1
b1011100 4
1$
#970
0$
#975
b1011101 #
b1011101 -
b1011101 .
b1011101 1
b1011101 4
1$
#980
0$
#985
b1011110 #
b1011110 -
b1011110 .
b1011110 1
b1011110 4
1$
#990
0$
#995
b1011111 #
b1011111 -
b1011111 .
b1011111 1
b1011111 4
1$
#1000
0$
#1005
b1100000 #
b1100000 -
b1100000 .
b1100000 1
b1100000 4
1$
#1010
0$
#1015
b1100001 #
b1100001 -
b1100001 .
b1100001 1
b1100001 4
1$
#1020
0$
#1025
b1100010 #
b1100010 -
b1100010 .
b1100010 1
b1100010 4
1$
#1030
0$
#1035
b1100011 #
b1100011 -
b1100011 .
b1100011 1
b1100011 4
1$
#1040
0$
#1045
b1100100 #
b1100100 -
b1100100 .
b1100100 1
b1100100 4
1$
#1050
0$
#1055
b1100101 #
b1100101 -
b1100101 .
b1100101 1
b1100101 4
1$
#1060
0$
#1065
b1100110 #
b1100110 -
b1100110 .
b1100110 1
b1100110 4
1$
#1070
0$
#1075
b1100111 #
b1100111 -
b1100111 .
b1100111 1
b1100111 4
1$
#1080
0$
#1085
b1101000 #
b1101000 -
b1101000 .
b1101000 1
b1101000 4
1$
#1090
0$
#1095
b1101001 #
b1101001 -
b1101001 .
b1101001 1
b1101001 4
1$
#1100
0$
#1105
b1101010 #
b1101010 -
b1101010 .
b1101010 1
b1101010 4
1$
#1110
0$
#1115
b1101011 #
b1101011 -
b1101011 .
b1101011 1
b1101011 4
1$
#1120
0$
#1125
b1101100 #
b1101100 -
b1101100 .
b1101100 1
b1101100 4
1$
#1130
0$
#1135
b1101101 #
b1101101 -
b1101101 .
b1101101 1
b1101101 4
1$
#1140
0$
#1145
b1101110 #
b1101110 -
b1101110 .
b1101110 1
b1101110 4
1$
#1150
0$
#1155
b1101111 #
b1101111 -
b1101111 .
b1101111 1
b1101111 4
1$
#1160
0$
#1165
b1110000 #
b1110000 -
b1110000 .
b1110000 1
b1110000 4
1$
#1170
0$
#1175
b1110001 #
b1110001 -
b1110001 .
b1110001 1
b1110001 4
1$
#1180
0$
#1185
b1110010 #
b1110010 -
b1110010 .
b1110010 1
b1110010 4
1$
#1190
0$
#1195
b1110011 #
b1110011 -
b1110011 .
b1110011 1
b1110011 4
1$
#1200
0$
#1205
b1110100 #
b1110100 -
b1110100 .
b1110100 1
b1110100 4
1$
#1210
0$
#1215
b1110101 #
b1110101 -
b1110101 .
b1110101 1
b1110101 4
1$
#1220
0$
#1225
b1110110 #
b1110110 -
b1110110 .
b1110110 1
b1110110 4
1$
#1230
0$
#1235
b1110111 #
b1110111 -
b1110111 .
b1110111 1
b1110111 4
1$
#1240
0$
#1245
b1111000 #
b1111000 -
b1111000 .
b1111000 1
b1111000 4
1$
#1250
0$
#1255
b1111001 #
b1111001 -
b1111001 .
b1111001 1
b1111001 4
1$
#1260
0$
#1265
b1111010 #
b1111010 -
b1111010 .
b1111010 1
b1111010 4
1$
#1270
0$
#1275
b1111011 #
b1111011 -
b1111011 .
b1111011 1
b1111011 4
1$
#1280
0$
#1285
b1111100 #
b1111100 -
b1111100 .
b1111100 1
b1111100 4
1$
#1290
0$
#1295
b1111101 #
b1111101 -
b1111101 .
b1111101 1
b1111101 4
1$
#1300
0$
#1305
b1111110 #
b1111110 -
b1111110 .
b1111110 1
b1111110 4
1$
#1310
0$
#1315
b1111111 #
b1111111 -
b1111111 .
b1111111 1
b1111111 4
1$
#1320
0$
#1325
b10000000 #
b10000000 -
b10000000 .
b10000000 1
b10000000 4
1$
#1330
0$
#1335
b10000001 #
b10000001 -
b10000001 .
b10000001 1
b10000001 4
1$
#1340
0$
#1345
b10000010 #
b10000010 -
b10000010 .
b10000010 1
b10000010 4
1$
#1350
0$
#1355
b10000011 #
b10000011 -
b10000011 .
b10000011 1
b10000011 4
1$
#1360
0$
#1365
b10000100 #
b10000100 -
b10000100 .
b10000100 1
b10000100 4
1$
#1370
0$
#1375
b10000101 #
b10000101 -
b10000101 .
b10000101 1
b10000101 4
1$
#1380
0$
#1385
b10000110 #
b10000110 -
b10000110 .
b10000110 1
b10000110 4
1$
#1390
0$
#1395
b10000111 #
b10000111 -
b10000111 .
b10000111 1
b10000111 4
1$
#1400
0$
#1405
b10001000 #
b10001000 -
b10001000 .
b10001000 1
b10001000 4
1$
#1410
0$
#1415
b10001001 #
b10001001 -
b10001001 .
b10001001 1
b10001001 4
1$
#1420
0$
#1425
b10001010 #
b10001010 -
b10001010 .
b10001010 1
b10001010 4
1$
#1430
0$
#1435
b10001011 #
b10001011 -
b10001011 .
b10001011 1
b10001011 4
1$
#1440
0$
#1445
b10001100 #
b10001100 -
b10001100 .
b10001100 1
b10001100 4
1$
#1450
0$
#1455
b10001101 #
b10001101 -
b10001101 .
b10001101 1
b10001101 4
1$
#1460
0$
#1465
b10001110 #
b10001110 -
b10001110 .
b10001110 1
b10001110 4
1$
#1470
0$
#1475
b10001111 #
b10001111 -
b10001111 .
b10001111 1
b10001111 4
1$
#1480
0$
#1485
b10010000 #
b10010000 -
b10010000 .
b10010000 1
b10010000 4
1$
#1490
0$
#1495
b10010001 #
b10010001 -
b10010001 .
b10010001 1
b10010001 4
1$
#1500
0$
#1505
b10010010 #
b10010010 -
b10010010 .
b10010010 1
b10010010 4
1$
#1510
0$
#1515
b10010011 #
b10010011 -
b10010011 .
b10010011 1
b10010011 4
1$
#1520
0$
#1525
b10010100 #
b10010100 -
b10010100 .
b10010100 1
b10010100 4
1$
#1530
0$
#1535
b10010101 #
b10010101 -
b10010101 .
b10010101 1
b10010101 4
1$
#1540
0$
#1545
b10010110 #
b10010110 -
b10010110 .
b10010110 1
b10010110 4
1$
#1550
0$
#1555
b10010111 #
b10010111 -
b10010111 .
b10010111 1
b10010111 4
1$
#1560
0$
#1565
b10011000 #
b10011000 -
b10011000 .
b10011000 1
b10011000 4
1$
#1570
0$
#1575
b10011001 #
b10011001 -
b10011001 .
b10011001 1
b10011001 4
1$
#1580
0$
#1585
b10011010 #
b10011010 -
b10011010 .
b10011010 1
b10011010 4
1$
#1590
0$
#1595
b10011011 #
b10011011 -
b10011011 .
b10011011 1
b10011011 4
1$
#1600
0$
#1605
b10011100 #
b10011100 -
b10011100 .
b10011100 1
b10011100 4
1$
#1610
0$
#1615
b10011101 #
b10011101 -
b10011101 .
b10011101 1
b10011101 4
1$
#1620
0$
#1625
b10011110 #
b10011110 -
b10011110 .
b10011110 1
b10011110 4
1$
#1630
0$
#1635
b10011111 #
b10011111 -
b10011111 .
b10011111 1
b10011111 4
1$
#1640
0$
#1645
b10100000 #
b10100000 -
b10100000 .
b10100000 1
b10100000 4
1$
#1650
0$
#1655
b10100001 #
b10100001 -
b10100001 .
b10100001 1
b10100001 4
1$
#1660
0$
#1665
b10100010 #
b10100010 -
b10100010 .
b10100010 1
b10100010 4
1$
#1670
0$
#1675
b10100011 #
b10100011 -
b10100011 .
b10100011 1
b10100011 4
1$
#1680
0$
#1685
b10100100 #
b10100100 -
b10100100 .
b10100100 1
b10100100 4
1$
#1690
0$
#1695
b10100101 #
b10100101 -
b10100101 .
b10100101 1
b10100101 4
1$
#1700
0$
#1705
b10100110 #
b10100110 -
b10100110 .
b10100110 1
b10100110 4
1$
#1710
0$
#1715
b10100111 #
b10100111 -
b10100111 .
b10100111 1
b10100111 4
1$
#1720
0$
#1725
b10101000 #
b10101000 -
b10101000 .
b10101000 1
b10101000 4
1$
#1730
0$
#1735
b10101001 #
b10101001 -
b10101001 .
b10101001 1
b10101001 4
1$
#1740
0$
#1745
b10101010 #
b10101010 -
b10101010 .
b10101010 1
b10101010 4
1$
#1750
0$
#1755
b10101011 #
b10101011 -
b10101011 .
b10101011 1
b10101011 4
1$
#1760
0$
#1765
b10101100 #
b10101100 -
b10101100 .
b10101100 1
b10101100 4
1$
#1770
0$
#1775
b10101101 #
b10101101 -
b10101101 .
b10101101 1
b10101101 4
1$
#1780
0$
#1785
b10101110 #
b10101110 -
b10101110 .
b10101110 1
b10101110 4
1$
#1790
0$
#1795
b10101111 #
b10101111 -
b10101111 .
b10101111 1
b10101111 4
1$
#1800
0$
#1805
b10110000 #
b10110000 -
b10110000 .
b10110000 1
b10110000 4
1$
#1810
0$
#1815
b10110001 #
b10110001 -
b10110001 .
b10110001 1
b10110001 4
1$
#1820
0$
#1825
b10110010 #
b10110010 -
b10110010 .
b10110010 1
b10110010 4
1$
#1830
0$
#1835
b10110011 #
b10110011 -
b10110011 .
b10110011 1
b10110011 4
1$
#1840
0$
#1845
b10110100 #
b10110100 -
b10110100 .
b10110100 1
b10110100 4
1$
#1850
0$
#1855
b10110101 #
b10110101 -
b10110101 .
b10110101 1
b10110101 4
1$
#1860
0$
#1865
b10110110 #
b10110110 -
b10110110 .
b10110110 1
b10110110 4
1$
#1870
0$
#1875
b10110111 #
b10110111 -
b10110111 .
b10110111 1
b10110111 4
1$
#1880
0$
#1885
b10111000 #
b10111000 -
b10111000 .
b10111000 1
b10111000 4
1$
#1890
0$
#1895
b10111001 #
b10111001 -
b10111001 .
b10111001 1
b10111001 4
1$
#1900
0$
#1905
b10111010 #
b10111010 -
b10111010 .
b10111010 1
b10111010 4
1$
#1910
0$
#1915
b10111011 #
b10111011 -
b10111011 .
b10111011 1
b10111011 4
1$
#1920
0$
#1925
b10111100 #
b10111100 -
b10111100 .
b10111100 1
b10111100 4
1$
#1930
0$
#1935
b10111101 #
b10111101 -
b10111101 .
b10111101 1
b10111101 4
1$
#1940
0$
#1945
b10111110 #
b10111110 -
b10111110 .
b10111110 1
b10111110 4
1$
#1950
0$
#1955
b10111111 #
b10111111 -
b10111111 .
b10111111 1
b10111111 4
1$
#1960
0$
#1965
b11000000 #
b11000000 -
b11000000 .
b11000000 1
b11000000 4
1$
#1970
0$
#1975
b11000001 #
b11000001 -
b11000001 .
b11000001 1
b11000001 4
1$
#1980
0$
#1985
b11000010 #
b11000010 -
b11000010 .
b11000010 1
b11000010 4
1$
#1990
0$
#1995
b11000011 #
b11000011 -
b11000011 .
b11000011 1
b11000011 4
1$
#2000
0$
#2005
b11000100 #
b11000100 -
b11000100 .
b11000100 1
b11000100 4
1$
#2010
0$
#2015
b11000101 #
b11000101 -
b11000101 .
b11000101 1
b11000101 4
1$
#2020
0$
#2025
b11000110 #
b11000110 -
b11000110 .
b11000110 1
b11000110 4
1$
#2030
0$
#2035
b11000111 #
b11000111 -
b11000111 .
b11000111 1
b11000111 4
1$
#2040
0$
#2045
b11001000 #
b11001000 -
b11001000 .
b11001000 1
b11001000 4
1$
#2050
0$
#2055
b11001001 #
b11001001 -
b11001001 .
b11001001 1
b11001001 4
1$
#2060
0$
#2065
b11001010 #
b11001010 -
b11001010 .
b11001010 1
b11001010 4
1$
#2070
0$
#2075
b11001011 #
b11001011 -
b11001011 .
b11001011 1
b11001011 4
1$
#2080
0$
#2085
b11001100 #
b11001100 -
b11001100 .
b11001100 1
b11001100 4
1$
#2090
0$
#2095
b11001101 #
b11001101 -
b11001101 .
b11001101 1
b11001101 4
1$
#2100
0$
#2105
b11001110 #
b11001110 -
b11001110 .
b11001110 1
b11001110 4
1$
#2110
0$
#2115
b11001111 #
b11001111 -
b11001111 .
b11001111 1
b11001111 4
1$
#2120
0$
#2125
b11010000 #
b11010000 -
b11010000 .
b11010000 1
b11010000 4
1$
#2130
0$
#2135
b11010001 #
b11010001 -
b11010001 .
b11010001 1
b11010001 4
1$
#2140
0$
#2145
b11010010 #
b11010010 -
b11010010 .
b11010010 1
b11010010 4
1$
#2150
0$
#2155
b11010011 #
b11010011 -
b11010011 .
b11010011 1
b11010011 4
1$
#2160
0$
#2165
b11010100 #
b11010100 -
b11010100 .
b11010100 1
b11010100 4
1$
#2170
0$
#2175
b11010101 #
b11010101 -
b11010101 .
b11010101 1
b11010101 4
1$
#2180
0$
#2185
b11010110 #
b11010110 -
b11010110 .
b11010110 1
b11010110 4
1$
#2190
0$
#2195
b11010111 #
b11010111 -
b11010111 .
b11010111 1
b11010111 4
1$
#2200
0$
#2205
b11011000 #
b11011000 -
b11011000 .
b11011000 1
b11011000 4
1$
#2210
0$
#2215
b11011001 #
b11011001 -
b11011001 .
b11011001 1
b11011001 4
1$
#2220
0$
#2225
b11011010 #
b11011010 -
b11011010 .
b11011010 1
b11011010 4
1$
#2230
0$
#2235
b11011011 #
b11011011 -
b11011011 .
b11011011 1
b11011011 4
1$
#2240
0$
#2245
b11011100 #
b11011100 -
b11011100 .
b11011100 1
b11011100 4
1$
#2250
0$
#2255
b11011101 #
b11011101 -
b11011101 .
b11011101 1
b11011101 4
1$
#2260
0$
#2265
b11011110 #
b11011110 -
b11011110 .
b11011110 1
b11011110 4
1$
#2270
0$
#2275
b11011111 #
b11011111 -
b11011111 .
b11011111 1
b11011111 4
1$
#2280
0$
#2285
b11100000 #
b11100000 -
b11100000 .
b11100000 1
b11100000 4
1$
#2290
0$
#2295
b11100001 #
b11100001 -
b11100001 .
b11100001 1
b11100001 4
1$
#2300
0$
#2305
b11100010 #
b11100010 -
b11100010 .
b11100010 1
b11100010 4
1$
#2310
0$
#2315
b11100011 #
b11100011 -
b11100011 .
b11100011 1
b11100011 4
1$
#2320
0$
#2325
b11100100 #
b11100100 -
b11100100 .
b11100100 1
b11100100 4
1$
#2330
0$
#2335
b11100101 #
b11100101 -
b11100101 .
b11100101 1
b11100101 4
1$
#2340
0$
#2345
b11100110 #
b11100110 -
b11100110 .
b11100110 1
b11100110 4
1$
#2350
0$
#2355
b11100111 #
b11100111 -
b11100111 .
b11100111 1
b11100111 4
1$
#2360
0$
#2365
b11101000 #
b11101000 -
b11101000 .
b11101000 1
b11101000 4
1$
#2370
0$
#2375
b11101001 #
b11101001 -
b11101001 .
b11101001 1
b11101001 4
1$
#2380
0$
#2385
b11101010 #
b11101010 -
b11101010 .
b11101010 1
b11101010 4
1$
#2390
0$
#2395
b11101011 #
b11101011 -
b11101011 .
b11101011 1
b11101011 4
1$
#2400
0$
#2405
b11101100 #
b11101100 -
b11101100 .
b11101100 1
b11101100 4
1$
#2410
0$
#2415
b11101101 #
b11101101 -
b11101101 .
b11101101 1
b11101101 4
1$
#2420
0$
#2425
b11101110 #
b11101110 -
b11101110 .
b11101110 1
b11101110 4
1$
#2430
0$
#2435
b11101111 #
b11101111 -
b11101111 .
b11101111 1
b11101111 4
1$
#2440
0$
#2445
b11110000 #
b11110000 -
b11110000 .
b11110000 1
b11110000 4
1$
#2450
0$
#2455
b11110001 #
b11110001 -
b11110001 .
b11110001 1
b11110001 4
1$
#2460
0$
#2465
b11110010 #
b11110010 -
b11110010 .
b11110010 1
b11110010 4
1$
#2470
0$
#2475
b11110011 #
b11110011 -
b11110011 .
b11110011 1
b11110011 4
1$
#2480
0$
#2485
b11110100 #
b11110100 -
b11110100 .
b11110100 1
b11110100 4
1$
#2490
0$
#2495
b11110101 #
b11110101 -
b11110101 .
b11110101 1
b11110101 4
1$
#2500
0$
#2505
b11110110 #
b11110110 -
b11110110 .
b11110110 1
b11110110 4
1$
#2510
0$
#2515
b11110111 #
b11110111 -
b11110111 .
b11110111 1
b11110111 4
1$
#2520
0$
#2525
b11111000 #
b11111000 -
b11111000 .
b11111000 1
b11111000 4
1$
#2530
0$
#2535
b11111001 #
b11111001 -
b11111001 .
b11111001 1
b11111001 4
1$
#2540
0$
#2545
b11111010 #
b11111010 -
b11111010 .
b11111010 1
b11111010 4
1$
#2550
0$
#2555
b11111011 #
b11111011 -
b11111011 .
b11111011 1
b11111011 4
1$
#2560
0$
#2565
b11111100 #
b11111100 -
b11111100 .
b11111100 1
b11111100 4
1$
#2570
0$
#2575
b11111101 #
b11111101 -
b11111101 .
b11111101 1
b11111101 4
1$
#2580
0$
#2585
b11111110 #
b11111110 -
b11111110 .
b11111110 1
b11111110 4
1$
#2590
0$
#2595
b11111111 #
b11111111 -
b11111111 .
b11111111 1
b11111111 4
1$
#2600
0$
#2605
b0 #
b0 -
b0 .
b0 1
b0 4
1$
#2610
0$
#2615
b1 #
b1 -
b1 .
b1 1
b1 4
1$
#2620
0$
#2625
b10 #
b10 -
b10 .
b10 1
b10 4
1$
#2630
0$
#2635
b11 #
b11 -
b11 .
b11 1
b11 4
1$
#2640
0$
#2645
b100 #
b100 -
b100 .
b100 1
b100 4
1$
#2650
0$
#2655
b101 #
b101 -
b101 .
b101 1
b101 4
1$
#2660
0$
#2665
b110 #
b110 -
b110 .
b110 1
b110 4
1$
#2670
0$
#2675
b111 #
b111 -
b111 .
b111 1
b111 4
1$
#2680
0$
#2685
b1000 #
b1000 -
b1000 .
b1000 1
b1000 4
1$
#2690
0$
#2695
b1001 #
b1001 -
b1001 .
b1001 1
b1001 4
1$
#2700
0$
#2705
b1010 #
b1010 -
b1010 .
b1010 1
b1010 4
1$
#2710
0$
#2715
b1011 #
b1011 -
b1011 .
b1011 1
b1011 4
1$
#2720
0$
#2725
b1100 #
b1100 -
b1100 .
b1100 1
b1100 4
1$
#2730
0$
